{
  "sprint_id": "SPRINT-004",
  "name": "SPRINT 180 — Fase 4-6 Máxima Iteración",
  "goal": "SPRINT 180 FASE 4 — Profundidad",
  "status": "closed",
  "tags": [],
  "sessions": [
    "BAGO-CHG-073",
    "tools/summary.py",
    "tools/tags.py",
    "tools/flow.py",
    "state/ESTADO_BAGO_ACTUAL.md"
  ],
  "artifacts": [
    "tools/findings_engine.py",
    "tools/scan.py",
    "tools/hotspot.py",
    "tools/autofix.py",
    "tools/gh_integration.py",
    "tools/risk_matrix.py",
    "tools/debt_ledger.py",
    "tools/impact_engine.py",
    "tools/contracts.py",
    "tools/bago_utils.py",
    "tools/testgen.py",
    "tools/ci_generator.py",
    "tools/bago_ask.py",
    "tools/velocity.py",
    "tools/patch.py",
    "tools/notes.py",
    "tools/template.py",
    "state/contracts/CONTRACT-001.json",
    "state/contracts/CONTRACT-002.json",
    "state/contracts/CONTRACT-003.json",
    "state/contracts/RULE-CDTR-001.json",
    "core/canon/REGLA_SALUD_RENDIMIENTO.md"
  ],
  "decisions": [
    "RULE-CDTR-001: código saludable = activo comercial medible",
    "Contratos con deadline verificables (C001 baseline, C002 T+2h, C003 T+4h)",
    "3 agentes paralelos para doc/lectura/validación en sprints largos",
    "testgen como herramienta canónica para repos desconocidos"
  ],
  "created_at": "2026-04-21T21:34:22.614175+00:00",
  "closed_at": "2026-04-21T23:02:06.402660+00:00",
  "summary": "Sprint 180 min completado al 100%: 40+ herramientas creadas (S1-S38 + F1-F6), pipeline salud→rendimiento comercial (risk_matrix, debt_ledger, impact_engine), sistema de contratos verificables (C001-C003, RULE-CDTR-001), 3 agentes paralelos (doc-updater, reader-agent, diff-agent), testgen para repos desconocidos, ci_generator, bago_ask, 48/48 tests ALL PASS, 71 routing entries, health 100/100, validate GO. CHG-078 registrado. datetime.now() corregido en 9 archivos."
}
