{
  "idea_index": 1,
  "idea_title": "Verificar cabinet al cerrar tarea",
  "priority": 79,
  "workflow": "W2_IMPLEMENTACION_CONTROLADA",
  "objetivo": "bago task --done muestra resumen del cabinet antes de cerrar.",
  "alcance": "Materializar la idea seleccionada con el menor cambio suficiente.",
  "no_alcance": "No expandir el alcance fuera de la idea elegida.",
  "archivos_candidatos": [
    ".bago/tools/emit_ideas.py"
  ],
  "validacion_minima": [
    "La salida debe explicar el cambio, los archivos y la verificación mínima.",
    "Métrica objetivo: bago task --done muestra resultado del cabinet al cerrar."
  ],
  "siguiente_paso": "Añadir bago cabinet como paso de verificación en show_task.py --done.",
  "metric": "bago task --done muestra resultado del cabinet al cerrar.",
  "contexto": [
    "Llamar a cabinet_orchestrator en el flujo de cierre."
  ],
  "status": "pending",
  "accepted_at": "2026-05-05T09:56:55.569820+00:00"
}